multiplier.v
module Sequential_Binary_Multiplier (Product, Ready, Multiplicand, Multiplier, Start,
clock, reset_b);
// Default configuration: five-bit datapath
parameter dp_width = 5; // Set to width of datapath
output [2*dp_width -1: 0] Product;
output Ready;
input [dp_width -1: 0] Multiplicand, Multiplier;
input Start, clock, reset_b;
parameter BC_size = 3; // Size of bit counter
parameter S_idle = 3'b001, // one-hot code

S_add = 3'b010,
S_shift = 3'b100;
reg [2: 0] state, next_state;
reg [dp_width -1: 0] A, B, Q; // Sized for datapath
reg C;
reg [BC_size -1: 0] P;
reg Load_regs, Decr_P, Add_regs, Shift_regs;
// Miscellaneous combinational logic
assign Product = {A, Q};
wire Zero = (P == 0); // counter is zero
// Zero = ~|P; // alternative
wire Ready = (state == S_idle); // controller status
// control unit
always @ ( posedge clock, negedge reset_b)
if (~reset_b) state <= S_idle; else state <= next_state;
always @ (state, Start, Q[0], Zero) begin
next_state = S_idle;
Load_regs = 0;
Decr_P = 0;
Add_regs = 0;
Shift_regs = 0;
case (state)
S_idle: begin if (Start) next_state = S_add; Load_regs = 1; end
S_add: begin next_state = S_shift; Decr_P = 1; if (Q[0]) Add_regs = 1; end
S_shift: begin Shift_regs = 1; if (Zero) next_state = S_idle;
else next_state = S_add; end
default : next_state = S_idle;
endcase
end
// datapath unit
always @ ( posedge clock) begin
if (Load_regs) begin
P <= dp_width;
A <= 0;
C <= 0;
B <= Multiplicand;
Q <= Multiplier;
end
if (Add_regs) {C, A} <= A + B;
if (Shift_regs) {C, A, Q} <= {C, A, Q} >> 1;
if (Decr_P) P <= P -1;
end
endmodule

tb_multiplier.v
module t_Sequential_Binary_Multiplier;
parameter dp_width = 5; // Set to width of datapath
wire [2*dp_width -1: 0] Product; // Output from multiplier
wire Ready;
reg [dp_width -1: 0] Multiplicand, Multiplier; // Inputs to multiplier
reg Start, clock, reset_b;
initial begin $dumpfile("tb_multiplier.vcd"); $dumpvars(0,t_Sequential_Binary_Multiplier); end
// Instantiate multiplier
Sequential_Binary_Multiplier M0 (Product, Ready, Multiplicand, Multiplier, Start, clock,
reset_b);
// Generate stimulus waveforms
initial #200 $finish;
initial
begin
Start = 0;
reset_b = 0;
#2 Start = 1; reset_b = 1;
Multiplicand = 5'b10111; Multiplier = 5'b10011;
#10 Start = 0;
end
initial
begin
clock = 0;
repeat (26) #5 clock = ~clock;
end
// Display results and compare with Table 8.5
always @ ( posedge clock)
$strobe ("C=%b A=%b Q=%b P=%b time=%0d",M0.C,M0.A,M0.Q,M0.P, $time);
endmodule

tb_multiplier.vcd
$date
	Wed Nov 22 10:14:27 2023
$end
$version
	Icarus Verilog
$end
$timescale
	1s
$end
$scope module t_Sequential_Binary_Multiplier $end
$var wire 10 ! Product [9:0] $end
$var wire 1 " Ready $end
$var reg 5 # Multiplicand [4:0] $end
$var reg 5 $ Multiplier [4:0] $end
$var reg 1 % Start $end
$var reg 1 & clock $end
$var reg 1 ' reset_b $end
$scope module M0 $end
$var wire 5 ( Multiplicand [4:0] $end
$var wire 5 ) Multiplier [4:0] $end
$var wire 10 * Product [9:0] $end
$var wire 1 " Ready $end
$var wire 1 + Start $end
$var wire 1 , Zero $end
$var wire 1 - clock $end
$var wire 1 . reset_b $end
$var reg 5 / A [4:0] $end
$var reg 1 0 Add_regs $end
$var reg 5 1 B [4:0] $end
$var reg 1 2 C $end
$var reg 1 3 Decr_P $end
$var reg 1 4 Load_regs $end
$var reg 3 5 P [2:0] $end
$var reg 5 6 Q [4:0] $end
$var reg 1 7 Shift_regs $end
$var reg 3 8 next_state [2:0] $end
$var reg 3 9 state [2:0] $end
$upscope $end
$upscope $end
$enddefinitions $end
#0
$dumpvars
b1 9
b1 8
07
bx 6
bx 5
14
03
x2
bx 1
00
bx /
0.
0-
x,
0+
bx *
bx )
bx (
0'
0&
0%
bx $
bx #
1"
bx !
$end
#2
b10 8
14
b10011 $
b10011 )
b10111 #
b10111 (
1'
1.
1%
1+
#5
10
13
04
b100 8
b10011 6
b10111 1
02
b0 /
b10011 !
b10011 *
b101 5
0,
b10 9
0"
1&
1-
#10
0&
0-
#12
10
13
b100 8
0%
0+
#15
17
00
03
b10 8
b100 5
b10111 /
b1011110011 !
b1011110011 *
b100 9
1&
1-
#20
0&
0-
#25
10
13
07
b100 8
b1011 /
b11001 6
b101111001 !
b101111001 *
b10 9
1&
1-
#30
0&
0-
#35
17
00
03
b10 8
b11 5
12
b10 /
b1011001 !
b1011001 *
b100 9
1&
1-
#40
0&
0-
#45
13
07
b100 8
02
b10001 /
b1100 6
b1000101100 !
b1000101100 *
b10 9
1&
1-
#50
0&
0-
#55
17
03
b10 8
b10 5
b100 9
1&
1-
#60
0&
0-
#65
13
07
b100 8
b1000 /
b10110 6
b100010110 !
b100010110 *
b10 9
1&
1-
#70
0&
0-
#75
17
03
b10 8
b1 5
b100 9
1&
1-
#80
0&
0-
#85
10
13
07
b100 8
b100 /
b1011 6
b10001011 !
b10001011 *
b10 9
1&
1-
#90
0&
0-
#95
17
00
03
b1 8
b0 5
1,
b11011 /
b1101101011 !
b1101101011 *
b100 9
1&
1-
#100
0&
0-
#105
14
07
b1101 /
b10101 6
b110110101 !
b110110101 *
b1 9
1"
1&
1-
#110
0&
0-
#115
14
b10011 6
b0 /
b10011 !
b10011 *
b101 5
0,
1&
1-
